CHANGES.txt
LICENSE.txt
MANIFEST.in
README.rst
setup.cfg
setup.py
tox.ini
blogdegins/__init__.py
blogdegins/__init__.pyc
blogdegins/getyesno.py
blogdegins/getyesno.pyc
blogdegins/main.py
blogdegins/main.pyc
blogdegins.egg-info/PKG-INFO
blogdegins.egg-info/SOURCES.txt
blogdegins.egg-info/dependency_links.txt
blogdegins.egg-info/entry_points.txt
blogdegins.egg-info/not-zip-safe
blogdegins.egg-info/requires.txt
blogdegins.egg-info/top_level.txt
blogdegins/_htmlrendercode/README.rst
blogdegins/_htmlrendercode/__init__.py
blogdegins/_htmlrendercode/assets.py
blogdegins/_htmlrendercode/assets.pyc
blogdegins/_htmlrendercode/base.js
blogdegins/_htmlrendercode/base.mako
blogdegins/_htmlrendercode/base.py
blogdegins/_htmlrendercode/base.scss
blogdegins/_htmlrendercode/content.js
blogdegins/_htmlrendercode/content.mako
blogdegins/_htmlrendercode/content.py
blogdegins/_htmlrendercode/content.scss
blogdegins/_htmlrendercode/mymako.py
blogdegins/_htmlrendercode/mymako.pyc
blogdegins/_htmlrendercode/page.pyc
blogdegins/_htmlrendercode/sample/__init__.py
blogdegins/_htmlrendercode/sample/__init__.pyc
blogdegins/_htmlrendercode/sample/aplic.pyc
blogdegins/_htmlrendercode/sample/sample.js
blogdegins/_htmlrendercode/sample/sample.mako
blogdegins/_htmlrendercode/sample/sample.py
blogdegins/_htmlrendercode/sample/sample.pyc
blogdegins/_htmlrendercode/sample/sample.scss
blogdegins/_htmlrendercode/scss-mixins/_ginsgrid.scss
blogdegins/_htmlrendercode/templates/logo.mako
blogdegins/_htmlrendercode/widgets/__init__.py
blogdegins/_htmlrendercode/widgets/__init__.pyc
blogdegins/_htmlrendercode/widgets/boxlist/__init__.py
blogdegins/_htmlrendercode/widgets/boxlist/__init__.pyc
blogdegins/_htmlrendercode/widgets/boxlist/boxlist.js
blogdegins/_htmlrendercode/widgets/boxlist/boxlist.mako
blogdegins/_htmlrendercode/widgets/boxlist/boxlist.py
blogdegins/_htmlrendercode/widgets/boxlist/boxlist.pyc
blogdegins/_htmlrendercode/widgets/boxlist/boxlist.scss
blogdegins/assets/README.txt
blogdegins/assets/h5bp+jquery/404.html
blogdegins/assets/h5bp+jquery/apple-touch-icon-114x114-precomposed.png
blogdegins/assets/h5bp+jquery/apple-touch-icon-144x144-precomposed.png
blogdegins/assets/h5bp+jquery/apple-touch-icon-57x57-precomposed.png
