Metadata-Version: 1.1
Name: blogdegins
Version: 0.5.0
Summary: Another static html code generator.
Home-page: https://bitbucket.org/artgins/blogdegins
Author: ginsmar
Author-email: ginsmar at artgins.com
License: MIT License
Keywords: html static generator blog ginsfsm ghtml mako webassets scss sass compass
Platform: UNKNOWN
Classifier: Intended Audience :: Developers
Classifier: Development Status :: 4 - Beta
Classifier: Environment :: Console
Classifier: Programming Language :: Python
Classifier: Programming Language :: Python :: 2
Classifier: Programming Language :: Python :: 2.7
Classifier: License :: OSI Approved :: MIT License
